lexilux/__init__.py
lexilux/_base.py
lexilux/chat.py
lexilux/chat_params.py
lexilux/embed.py
lexilux/embed_params.py
lexilux/exceptions.py
lexilux/rerank.py
lexilux/tokenizer.py
lexilux/usage.py
lexilux/chat/__init__.py
lexilux/chat/client.py
lexilux/chat/continue_.py
lexilux/chat/exceptions.py
lexilux/chat/formatters.py
lexilux/chat/history.py
lexilux/chat/models.py
lexilux/chat/params.py
lexilux/chat/streaming.py
lexilux/chat/utils.py
lexilux-2.2.0.dist-info/licenses/LICENSE
scripts/generate_release_notes.py
lexilux-2.2.0.dist-info/METADATA
lexilux-2.2.0.dist-info/WHEEL
lexilux-2.2.0.dist-info/top_level.txt
lexilux-2.2.0.dist-info/RECORD
