Metadata-Version: 2.4
Name: lexilux
Version: 2.2.0
Summary: Unified LLM API client library with Chat, Embedding, Rerank, and Tokenizer support
Author: Lexilux Team
License: Apache-2.0
Project-URL: Homepage, https://github.com/lzjever/lexilux
Project-URL: Documentation, https://lexilux.readthedocs.io
Project-URL: Repository, https://github.com/lzjever/lexilux
Project-URL: Issues, https://github.com/lzjever/lexilux/issues
Keywords: llm,api,chat,embedding,rerank,tokenizer,openai-compatible
Classifier: Development Status :: 4 - Beta
Classifier: Intended Audience :: Developers
Classifier: Programming Language :: Python :: 3
Classifier: Programming Language :: Python :: 3.8
Classifier: Programming Language :: Python :: 3.9
Classifier: Programming Language :: Python :: 3.10
Classifier: Programming Language :: Python :: 3.11
Classifier: Programming Language :: Python :: 3.12
Classifier: Programming Language :: Python :: 3.13
Classifier: Programming Language :: Python :: 3.14
Classifier: Topic :: Software Development :: Libraries :: Python Modules
Requires-Python: <3.15,>=3.8
License-File: LICENSE
Requires-Dist: requests>=2.28.0
Provides-Extra: tokenizer
Requires-Dist: transformers>=4.30.0; extra == "tokenizer"
Requires-Dist: tokenizers>=0.13.0; extra == "tokenizer"
Requires-Dist: huggingface-hub>=0.16.0; extra == "tokenizer"
Provides-Extra: dev
Requires-Dist: pytest>=7.0.0; extra == "dev"
Requires-Dist: pytest-cov>=4.0.0; extra == "dev"
Requires-Dist: pytest-mock>=3.10.0; extra == "dev"
Requires-Dist: sphinx>=5.0.0; extra == "dev"
Requires-Dist: sphinx-rtd-theme>=1.0.0; extra == "dev"
Requires-Dist: ruff>=0.1.0; extra == "dev"
Requires-Dist: mypy>=0.991; extra == "dev"
Provides-Extra: docs
Requires-Dist: sphinx<9.0.0,>=5.0.0; extra == "docs"
Requires-Dist: sphinx-rtd-theme>=1.0.0; extra == "docs"
Requires-Dist: furo>=2024.1.0; extra == "docs"
Requires-Dist: sphinx-autodoc-typehints>=1.19.0; extra == "docs"
Requires-Dist: sphinx-copybutton>=0.5.0; extra == "docs"
Requires-Dist: sphinx-design>=0.5.0; extra == "docs"
Dynamic: license-file
